setup.cfg
setup.py
examples/__init__.py
examples/three_word_index.py
human_word_indexes/__init__.py
human_word_indexes/word_index_filter.py
human_word_indexes/word_index_generator.py
human_word_indexes.egg-info/PKG-INFO
human_word_indexes.egg-info/SOURCES.txt
human_word_indexes.egg-info/dependency_links.txt
human_word_indexes.egg-info/requires.txt
human_word_indexes.egg-info/top_level.txt