Metadata-Version: 1.2
Name: human-word-indexes
Version: 1.1
Summary: A Package to generate human readable indexes for Pandas DataFrames or other data
Home-page: https://github.com/wooddar/human_word_indexes
Author: hugodarwood
Author-email: hugodarwood@gmail.com
License: MIT
Download-URL: https://github.com/wooddar/human_word_indexes/archive/0.1.tar.gz
Platform: UNKNOWN
Requires-Python: >=2.7
